{
  "db_name": "PostgreSQL",
  "query": "\n                SELECT height FROM blocks \n                WHERE height >= $1 AND height <= $2 \n                ORDER BY height\n                ",
  "describe": {
    "columns": [
      {
        "ordinal": 0,
        "name": "height",
        "type_info": "Int8"
      }
    ],
    "parameters": {
      "Left": [
        "Int8",
        "Int8"
      ]
    },
    "nullable": [
      false
    ]
  },
  "hash": "46cbb68327ce915b99027e5467b2f37179728e9978f12d699b4cc98715923eb9"
}
