{
  "db_name": "PostgreSQL",
  "query": "SELECT * FROM transactions WHERE txid = $1",
  "describe": {
    "columns": [
      {
        "ordinal": 0,
        "name": "txid",
        "type_info": "Text"
      },
      {
        "ordinal": 1,
        "name": "block_height",
        "type_info": "Int8"
      },
      {
        "ordinal": 2,
        "name": "data",
        "type_info": "Jsonb"
      },
      {
        "ordinal": 3,
        "name": "status",
        "type_info": "Jsonb"
      },
      {
        "ordinal": 4,
        "name": "bitcoin_txids",
        "type_info": "TextArray"
      },
      {
        "ordinal": 5,
        "name": "created_at",
        "type_info": "Timestamptz"
      }
    ],
    "parameters": {
      "Left": [
        "Text"
      ]
    },
    "nullable": [
      false,
      false,
      false,
      false,
      true,
      false
    ]
  },
  "hash": "9c6e44c79e79f226116cd3a8a96242c70af183e424a6a2727c1fc12564d29287"
}
